{
	"targets": [
		"0_translucent",
		"0_itemEntity",
		"0_particles",
		"0_clouds",
		"0_weather",
		"0",
		"1",
		"2",
		"3",
		"4",
		"5",
		"6",
		"7"
	],
	"passes": [
		{
			"name": "perspective:outlined",
			"intarget": "minecraft:main",
			"outtarget": "0",
			"auxtargets": [
				{
					"name": "DiffuseDepthSampler",
					"id": "minecraft:main:depth"
				},
				{
					"name": "TranslucentSampler",
					"id": "0_translucent"
				},
				{
					"name": "TranslucentDepthSampler",
					"id": "0_translucent:depth"
				},
				{
					"name": "ItemEntitySampler",
					"id": "0_itemEntity"
				},
				{
					"name": "ItemEntityDepthSampler",
					"id": "0_itemEntity:depth"
				},
				{
					"name": "ParticlesSampler",
					"id": "0_particles"
				},
				{
					"name": "ParticlesDepthSampler",
					"id": "0_particles:depth"
				},
				{
					"name": "CloudsSampler",
					"id": "0_clouds"
				},
				{
					"name": "CloudsDepthSampler",
					"id": "0_clouds:depth"
				},
				{
					"name": "WeatherSampler",
					"id": "0_weather"
				},
				{
					"name": "WeatherDepthSampler",
					"id": "0_weather:depth"
				}
			],
			"uniforms": [
				{
					"name": "Strength",
					"values": [ 0.25 ]
				}
			]
		},
		{
			"name": "perspective:fog",
			"intarget": "0",
			"outtarget": "1",
			"auxtargets": [
				{
					"name": "DiffuseDepthSampler",
					"id": "minecraft:main:depth"
				}
			],
			"uniforms": [
				{
					"name": "Thickness",
					"values": [ 256.0 ]
				}
			]
		},
		{
			"name": "perspective:reduced_colors",
			"intarget": "1",
			"outtarget": "2",
			"uniforms": [
				{
					"name": "Amount",
					"values": [ 8.0 ]
				}
			]
		},
		{
			"name": "downscale",
			"intarget": "2",
			"outtarget": "3"
		},
		{
			"name": "perspective:pixelated",
			"intarget": "3",
			"outtarget": "4",
			"uniforms": [
				{
					"name": "Amount",
					"values": [ 4.0 ]
				}
			]
		},
		{
			"name": "notch",
			"intarget": "4",
			"outtarget": "5",
			"auxtargets": [
				{
					"name": "DitherSampler",
					"id": "dither",
					"width": 32,
					"height": 32,
					"bilinear": true
				}
			]
		},




		{
			"name": "perspective:scanlines",
			"intarget": "5",
			"outtarget": "6"
		},
		{
			"name": "perspective:aspect_ratio",
			"intarget": "6",
			"outtarget": "7",
			"uniforms": [
				{
					"name": "AspectRatio",
					"values": [ 4.0, 3.0 ]
				},
				{
					"name": "BorderColor",
					"values": [ 0.0, 0.0, 0.0 ]
				}
			]
		},
		{
			"name": "blit",
			"intarget": "7",
			"outtarget": "minecraft:main"
		}
	]
}
